ditlep
